saas_base/__init__.py
saas_base/admin.py
saas_base/apps.py
saas_base/ipware.py
saas_base/middleware.py
saas_base/permissions.py
saas_base/secure.py
saas_base/settings.py
saas_base/settings.pyi
saas_base/signals.py
saas_base/spectacular_schema.py
saas_base/test.py
saas_base/api_urls/__init__.py
saas_base/api_urls/all.py
saas_base/api_urls/auth.py
saas_base/api_urls/groups.py
saas_base/api_urls/members.py
saas_base/api_urls/tenants.py
saas_base/api_urls/user.py
saas_base/api_urls/user_emails.py
saas_base/api_urls/user_members.py
saas_base/auth/__init__.py
saas_base/auth/backends.py
saas_base/db/__init__.py
saas_base/db/cache.py
saas_base/db/fields.py
saas_base/db/manager.py
saas_base/db/migrate_receiver.py
saas_base/drf/__init__.py
saas_base/drf/apps.py
saas_base/drf/decorators.py
saas_base/drf/errors.py
saas_base/drf/filters.py
saas_base/drf/permissions.py
saas_base/drf/serializers.py
saas_base/drf/spectacular.py
saas_base/drf/spectacular_schema.py
saas_base/drf/views.py
saas_base/endpoints/__init__.py
saas_base/endpoints/auth.py
saas_base/endpoints/groups.py
saas_base/endpoints/members.py
saas_base/endpoints/password.py
saas_base/endpoints/permissions.py
saas_base/endpoints/roles.py
saas_base/endpoints/tenant.py
saas_base/endpoints/user.py
saas_base/endpoints/user_emails.py
saas_base/endpoints/user_members.py
saas_base/fixtures/test_data.yaml
saas_base/functions/__init__.py
saas_base/functions/ip.py
saas_base/locale/de/LC_MESSAGES/django.mo
saas_base/locale/de/LC_MESSAGES/django.po
saas_base/locale/es/LC_MESSAGES/django.mo
saas_base/locale/es/LC_MESSAGES/django.po
saas_base/locale/fr/LC_MESSAGES/django.mo
saas_base/locale/fr/LC_MESSAGES/django.po
saas_base/locale/ja/LC_MESSAGES/django.mo
saas_base/locale/ja/LC_MESSAGES/django.po
saas_base/locale/zh/LC_MESSAGES/django.mo
saas_base/locale/zh/LC_MESSAGES/django.po
saas_base/management/__init__.py
saas_base/management/commands/__init__.py
saas_base/management/commands/secrets.py
saas_base/migrations/0001_initial.py
django_saas_base-0.13.1.dist-info/METADATA
django_saas_base-0.13.1.dist-info/WHEEL
django_saas_base-0.13.1.dist-info/RECORD
